[
    {
        "Название": "acura tl 2009-2014 фара зад задней левая, левой usa",
        "Цена": "5746грн",
        "Доставка": "1437"
    },
    {
        "Название": "хонда accord acura tsx листва порога левая, левой оригинал",
        "Цена": "2387грн",
        "Доставка": "597"
    },
    {
        "Название": "ключи acura mdx 2019+ ключ smart key пульт, пульта",
        "Цена": "13100грн",
        "Доставка": "3275"
    },
    {
        "Название": "ключ acura mdx 2014-2019 ключ smart key пульт, пульта",
        "Цена": "6448грн",
        "Доставка": "1612"
    },
    {
        "Название": "acura mdx 10-13 бампер зад задний",
        "Цена": "10836грн",
        "Доставка": "2710"
    },
    {
        "Название": "хонда accord acura диск алюминиевые, алюминиевое  17\" 7. 5x17 et55",
        "Цена": "3253грн",
        "Доставка": "814"
    },
    {
        "Название": "блок розжига митсубиси  электрический хонда acura",
        "Цена": "2688грн",
        "Доставка": "672"
    },
    {
        "Название": "acura rdx 13- ремень панель  перед передний усиление r usa",
        "Цена": "9174грн",
        "Доставка": "2294"
    },
    {
        "Название": "acura tl фара левый перед левая, левой передней",
        "Цена": "4868грн",
        "Доставка": "1218"
    },
    {
        "Название": "бампер перед передний acura tl 2009-2011",
        "Цена": "10436грн",
        "Доставка": "2610"
    },
    {
        "Название": "бампер зад задний задний acura mdx ii 2007-2009",
        "Цена": "14796грн",
        "Доставка": "3700"
    },
    {
        "Название": "отражатель бампера зад задний левый acura mdx ii 07-09",
        "Цена": "2431грн",
        "Доставка": "608"
    },
    {
        "Название": "отражатель бампера зад задний правый acura mdx ii 07-",
        "Цена": "2431грн",
        "Доставка": "608"
    },
    {
        "Название": "крышка бампера крюк зад задней acura mdx ii 07-",
        "Цена": "1724грн",
        "Доставка": "431"
    },
    {
        "Название": "вал приводной acura mdx и хонда пульт, пульта 3. 5 v6 01-06r",
        "Цена": "4868грн",
        "Доставка": "1218"
    },
    {
        "Название": "хонда acura crv пластик под двигатель 74561-ta0-a00",
        "Цена": "995грн",
        "Доставка": "249"
    },
    {
        "Название": "acura tl крыло левый перед передний b68p 97r",
        "Цена": "2740грн",
        "Доставка": "686"
    },
    {
        "Название": "acura ilx 2016-2018 фара лед фара перед usa",
        "Цена": "22239грн",
        "Доставка": "5560"
    },
    {
        "Название": "acura tl и 95-98 держатель перед левый 76600sw5a01",
        "Цена": "1260грн",
        "Доставка": "315"
    },
    {
        "Название": "acura rdx 2016-2018 фара зад задней левая, левой usa",
        "Цена": "9183грн",
        "Доставка": "2296"
    },
    {
        "Название": "acura rdx 2016-2018 фара зад задней правая usa",
        "Цена": "7500грн",
        "Доставка": "1876"
    },
    {
        "Название": "бардачок на plyty acura tl 1999r.",
        "Цена": "928грн",
        "Доставка": "233"
    },
    {
        "Название": "acura mdx 2014-2020 фара зад задней левая, левой usa",
        "Цена": "4430грн",
        "Доставка": "1108"
    },
    {
        "Название": "acura mdx 14-17r. фара левый фара лед usa",
        "Цена": "22230грн",
        "Доставка": "5558"
    },
    {
        "Название": "acura tl 2009-2014 фара зад задней правая usa",
        "Цена": "5746грн",
        "Доставка": "1437"
    },
    {
        "Название": "acura rdx 2016-2018 фара зад задней правая лед usa",
        "Цена": "4860грн",
        "Доставка": "1215"
    },
    {
        "Название": "acura rdx 2013-2015 фара зад задней правая usa",
        "Цена": "4860грн",
        "Доставка": "1215"
    },
    {
        "Название": "acura tl и 95-98 держатель перед правое 76610sl5a01",
        "Цена": "1260грн",
        "Доставка": "315"
    },
    {
        "Название": "acura mdx 2017-2020 фара фара правая лед usa",
        "Цена": "30701грн",
        "Доставка": "7676"
    },
    {
        "Название": "acura rdx 2019 2020- зеркало левый камера usa",
        "Цена": "17887грн",
        "Доставка": "4472"
    },
    {
        "Название": "поддон, миски поддон, миски масла, маслом  хонда acura tl 2. 5 r5 20v 96r",
        "Цена": "1193грн",
        "Доставка": "299"
    },
    {
        "Название": "acura mdx 2014-2017 бампер перед колпачки usa",
        "Цена": "23057грн",
        "Доставка": "5765"
    },
    {
        "Название": "acura ilx 2016-2018 фара лед фара перед usa",
        "Цена": "25285грн",
        "Доставка": "6322"
    },
    {
        "Название": "acura mdx 2014-2017 фара фара левая, левой лед usa",
        "Цена": "25285грн",
        "Доставка": "6322"
    },
    {
        "Название": "бампер перед хонда acura 99-04",
        "Цена": "9035грн",
        "Доставка": "2259"
    },
    {
        "Название": "acura mdx 2014-2017 фара фара левая, левой лед usa",
        "Цена": "16581грн",
        "Доставка": "4146"
    },
    {
        "Название": "acura mdx 2014-2017 решетка решетка, решетки перед решетка, решетки",
        "Цена": "13526грн",
        "Доставка": "3382"
    },
    {
        "Название": "рычаг задний зад l/p acura mdx и хонда пульт, пульта комплект.",
        "Цена": "1636грн",
        "Доставка": "409"
    },
    {
        "Название": "хонда legend acura rl ремень панель  задний ванна место для запаски",
        "Цена": "7500грн",
        "Доставка": "1876"
    },
    {
        "Название": "acura rdx 2006-2012 крышка зад задней багажника usa",
        "Цена": "32376грн",
        "Доставка": "8095"
    },
    {
        "Название": "acura rdx 2013-2015 крышка зад задней багажника usa",
        "Цена": "33680грн",
        "Доставка": "8421"
    },
    {
        "Название": "acura mdx 2014-2017 бампер перед колпачки usa",
        "Цена": "19576грн",
        "Доставка": "4894"
    },
    {
        "Название": "крышка багажника задней зад acura rl 2004-2009",
        "Цена": "12177грн",
        "Доставка": "3045"
    },
    {
        "Название": "acura mdx 2014-2020 крышка зад задней багажника usa",
        "Цена": "17843грн",
        "Доставка": "4461"
    },
    {
        "Название": "acura mdx 2007-2013 крышка зад замок багажника usa",
        "Цена": "23928грн",
        "Доставка": "5982"
    },
    {
        "Название": "рычаг задний зад левый acura mdx и хонда пульт, пульта",
        "Цена": "2254грн",
        "Доставка": "564"
    },
    {
        "Название": "acura mdx рестайлинг 2017-2019 бампер зад задний usa",
        "Цена": "25908грн",
        "Доставка": "6477"
    },
    {
        "Название": "acura rdx рестайлинг 2016- бампер перед крышка usa",
        "Цена": "21316грн",
        "Доставка": "5330"
    },
    {
        "Название": "рычаг задний зад правый acura mdx и хонда пульт, пульта",
        "Цена": "2696грн",
        "Доставка": "675"
    },
    {
        "Название": "переключатель аварийных acura tl",
        "Цена": "1074грн",
        "Доставка": "269"
    },
    {
        "Название": "zagarek acura tl",
        "Цена": "928грн",
        "Доставка": "233"
    },
    {
        "Название": "acura t 3. 2 v6 защита двигателя верхний, горы",
        "Цена": "1547грн",
        "Доставка": "387"
    },
    {
        "Название": "acura tlx 2018-2020 фара фара перед лед usa",
        "Цена": "34735грн",
        "Доставка": "8684"
    },
    {
        "Название": "acura tlx 2021- фара фара левая, левой full лед usa",
        "Цена": "39019грн",
        "Доставка": "9755"
    },
    {
        "Название": "acura mdx 8,5x20 et50 tyr20085a 42800-tyr-a20",
        "Цена": "37691грн",
        "Доставка": "9423"
    },
    {
        "Название": "крыло левый acura rsx integra dc5 05 06",
        "Цена": "7061грн",
        "Доставка": "1766"
    },
    {
        "Название": "суппорт тормозной правый зад acura tl 1999r.",
        "Цена": "1282грн",
        "Доставка": "321"
    },
    {
        "Название": "acura mdx 2014-2016 капот перед крышка алюминиевые, алюминиевое  usa",
        "Цена": "17843грн",
        "Доставка": "4461"
    },
    {
        "Название": "acura ilx 2013-2018 капот перед крышка крышка usa",
        "Цена": "19584грн",
        "Доставка": "4896"
    },
    {
        "Название": "тормозные диски, диск тормозов перед kpt acura tl 3, 2 b 1999r.",
        "Цена": "1627грн",
        "Доставка": "407"
    },
    {
        "Название": "acura rdx 2019 2020- капот перед крышка крышка",
        "Цена": "21760грн",
        "Доставка": "5440"
    },
    {
        "Название": "сиденье кожа правый передний acura mdx ii 2007-12",
        "Цена": "6140грн",
        "Доставка": "1536"
    },
    {
        "Название": "зеркало левый 11 pin acura mdx ii 2011 nh737m",
        "Цена": "8026грн",
        "Доставка": "2007"
    },
    {
        "Название": "блок розжига ксенон, ксенону acura tsx tl rl хонда accord",
        "Цена": "1804грн",
        "Доставка": "451"
    },
    {
        "Название": "acura ilx 2013-2018 капот перед крышка крышка usa",
        "Цена": "19584грн",
        "Доставка": "4896"
    },
    {
        "Название": "хонда accord acura диск алюминиевые, алюминиевое  17\" 7. 5x17 et55",
        "Цена": "3253грн",
        "Доставка": "814"
    },
    {
        "Название": "панель печкой и кондиционера acura tl 1999r.",
        "Цена": "1273грн",
        "Доставка": "319"
    },
    {
        "Название": "фара правая передней acura mdx-1 mdx 1 и 01-06",
        "Цена": "1370грн",
        "Доставка": "343"
    },
    {
        "Название": "acura mdx крышка багажника",
        "Цена": "14179грн",
        "Доставка": "3545"
    },
    {
        "Название": "стартер acura mdx md-x 07-09 3. 7 автомат",
        "Цена": "5211грн",
        "Доставка": "1303"
    },
    {
        "Название": "acura tlx 2020 2021- бампер зад задний usa",
        "Цена": "18278грн",
        "Доставка": "4570"
    },
    {
        "Название": "переключатель спаренний acura tl 1999r.",
        "Цена": "1096грн",
        "Доставка": "275"
    },
    {
        "Название": "acura mdx рестайлинг 2017-2019 бампер зад задний usa",
        "Цена": "19576грн",
        "Доставка": "4894"
    },
    {
        "Название": "хонда acura ilx 2019 2020 бампер перед usa",
        "Цена": "18705грн",
        "Доставка": "4677"
    },
    {
        "Название": "acura tlx 2015 2016 2017 бампер перед передний usa",
        "Цена": "15667грн",
        "Доставка": "3917"
    },
    {
        "Название": "полуось передней левая, левой хонда legend iv kb1 kb-1 acura",
        "Цена": "1636грн",
        "Доставка": "409"
    },
    {
        "Название": "хонда acura решетка, решетки гриль",
        "Цена": "1105грн",
        "Доставка": "277"
    },
    {
        "Название": "цапфа ступица перед l/p acura mdx и хонда пульт, пульта",
        "Цена": "2696грн",
        "Доставка": "675"
    },
    {
        "Название": "цапфа передней перед правая хонда acura 12-15",
        "Цена": "7492грн",
        "Доставка": "1873"
    },
    {
        "Название": "acura rdx 2013- фара фара перед ксенон, ксенону r usa",
        "Цена": "22230грн",
        "Доставка": "5558"
    },
    {
        "Название": "хонда acura nsx тормозные диски, диск комплект. диск перед зад 2018",
        "Цена": "452565грн",
        "Доставка": "113142"
    },
    {
        "Название": "новый, новое диски brock b36 2020rok maserati acura jeep",
        "Цена": "31780грн",
        "Доставка": "7946"
    },
    {
        "Название": "acura ключ пульт, пульта оригинал",
        "Цена": "3138грн",
        "Доставка": "785"
    },
    {
        "Название": "acura rlx 2014-2017 фара лед drl галоген usa",
        "Цена": "18757грн",
        "Доставка": "4690"
    },
    {
        "Название": "новый, новое диски brock b36 2020rok maserati acura jeep",
        "Цена": "31780грн",
        "Доставка": "7946"
    },
    {
        "Название": "acura tlx 2018 2019 бампер перед передний usa",
        "Цена": "19576грн",
        "Доставка": "4894"
    },
    {
        "Название": "acura tlx 2018 2019 бампер перед передний usa",
        "Цена": "19576грн",
        "Доставка": "4894"
    },
    {
        "Название": "acura tl 2004 2005 2006 бампер зад задний usa",
        "Цена": "13491грн",
        "Доставка": "3373"
    },
    {
        "Название": "acura tlx 2018 2019 2020 бампер зад задний usa",
        "Цена": "17408грн",
        "Доставка": "4352"
    },
    {
        "Название": "acura mdx рестайлинг 2017-2019 бампер зад задний usa",
        "Цена": "13491грн",
        "Доставка": "3373"
    },
    {
        "Название": "acura rdx 2019 2020- бампер перед передний usa",
        "Цена": "19576грн",
        "Доставка": "4894"
    },
    {
        "Название": "acura mdx 2010-2013 бампер перед передний usa",
        "Цена": "15232грн",
        "Доставка": "3808"
    },
    {
        "Название": "хонда acura ilx 2019 20 бампер перед хром, хромом usa",
        "Цена": "19576грн",
        "Доставка": "4894"
    },
    {
        "Название": "механизм моторчик стеклоочистителей acura tl 1999r.",
        "Цена": "1370грн",
        "Доставка": "343"
    },
    {
        "Название": "бампер перед передний acura tl",
        "Цена": "23928грн",
        "Доставка": "5982"
    },
    {
        "Название": "acura rdx 2016 2017 2018 бампер зад задний usa",
        "Цена": "15224грн",
        "Доставка": "3806"
    },
    {
        "Название": "хонда acura mdx 2010 2011 2012 бампер зад usa",
        "Цена": "10880грн",
        "Доставка": "2720"
    },
    {
        "Название": "acura tlx 2015 2016 2017 бампер зад задний usa",
        "Цена": "15224грн",
        "Доставка": "3806"
    },
    {
        "Название": "хонда acura mdx рестайлинг 2017- бампер перед usa",
        "Цена": "15224грн",
        "Доставка": "3806"
    },
    {
        "Название": "acura tlx 2018 2019 бампер перед передний usa",
        "Цена": "19576грн",
        "Доставка": "4894"
    },
    {
        "Название": "хонда acura mdx 2014 2015 2016 бампер перед usa",
        "Цена": "15224грн",
        "Доставка": "3806"
    },
    {
        "Название": "acura tlx sport 2018 2019 бампер зад задний usa",
        "Цена": "19576грн",
        "Доставка": "4894"
    },
    {
        "Название": "двигатель хонда 3. v6 j30a accord acura legend jdm",
        "Цена": "37314грн",
        "Доставка": "9329"
    },
    {
        "Название": "хонда nsx acura 2016- 21 крыло левый передний",
        "Цена": "52692грн",
        "Доставка": "13173"
    },
    {
        "Название": "радио сменник  cd хонда legend kb1 acura rl",
        "Цена": "4517грн",
        "Доставка": "1130"
    },
    {
        "Название": "рычаг перед acura rsx 2001 2006 левый",
        "Цена": "1361грн",
        "Доставка": "341"
    },
    {
        "Название": "рычаг перед acura rsx 2001 2006 правый",
        "Цена": "1361грн",
        "Доставка": "341"
    },
    {
        "Название": "ступица цапфа acura rsx 2001 2006 правая",
        "Цена": "4013грн",
        "Доставка": "1004"
    },
    {
        "Название": "вентилятор внутри вентилятор печки acura tl 1999r.",
        "Цена": "1096грн",
        "Доставка": "275"
    },
    {
        "Название": "зеркало левый електрическое, электрическое  acura tl 1999r.",
        "Цена": "2688грн",
        "Доставка": "672"
    },
    {
        "Название": "фара правая задней acura tl 1999r.",
        "Цена": "1980грн",
        "Доставка": "496"
    },
    {
        "Название": "фара правый фара acura tl 1999r.",
        "Цена": "2599грн",
        "Доставка": "650"
    },
    {
        "Название": "фара левая, левой задней acura tl 1999r.",
        "Цена": "1980грн",
        "Доставка": "496"
    },
    {
        "Название": "acura zdx 2009- фара фара перед ксенон, ксенону l usa",
        "Цена": "17878грн",
        "Доставка": "4470"
    },
    {
        "Название": "acura rl 2005-2008 фара фара ксенон, ксенону левая, левой usa",
        "Цена": "9174грн",
        "Доставка": "2294"
    },
    {
        "Название": "acura rdx 2006- фара фара перед ксенон, ксенону r usa",
        "Цена": "9183грн",
        "Доставка": "2296"
    },
    {
        "Название": "рейка рулевая acura tl 2007r 3. 2",
        "Цена": "5746грн",
        "Доставка": "1437"
    },
    {
        "Название": "блок розжига ксенон, ксенону мазда 5 3 acura w3t15671",
        "Цена": "2033грн",
        "Доставка": "509"
    },
    {
        "Название": "блок розжига ксенон, ксенону мазда 5 3 acura w3t15671",
        "Цена": "2033грн",
        "Доставка": "509"
    },
    {
        "Название": "двигатель acura 2. citd",
        "Цена": "21760грн",
        "Доставка": "5440"
    },
    {
        "Название": "лямбда - зонд лямбда зонд, лямбда - зонд acura rl 3. 5",
        "Цена": "1547грн",
        "Доставка": "387"
    },
    {
        "Название": "блок розжига фары митсубиси  хонда acura",
        "Цена": "1538грн",
        "Доставка": "385"
    },
    {
        "Название": "бампер перед передний хонда acura tsx",
        "Цена": "7500грн",
        "Доставка": "1876"
    },
    {
        "Название": "цапфа ступица acura tl 2007r",
        "Цена": "4868грн",
        "Доставка": "1218"
    },
    {
        "Название": "acura tl дверь зад левый состояние  идеальный.",
        "Цена": "4824грн",
        "Доставка": "1207"
    },
    {
        "Название": "катушка зажигания хонда legend acura 3. 5",
        "Цена": "928грн",
        "Доставка": "233"
    },
    {
        "Название": "клапан egr хонда acura mdx 3. 5 v6 03-06r 80tys миль",
        "Цена": "1591грн",
        "Доставка": "398"
    },
    {
        "Название": "зеркало стекло вклад левый левый acura tl 09-14",
        "Цена": "1538грн",
        "Доставка": "385"
    },
    {
        "Название": "acura rdx 2016- фара фара r перед usa лед",
        "Цена": "17887грн",
        "Доставка": "4472"
    },
    {
        "Название": "полуось правая шрус зад acura mdx 1 и 3. 5 v6 03r",
        "Цена": "2688грн",
        "Доставка": "672"
    },
    {
        "Название": "acura mdx 2014-2017 бампер перед передний решетка",
        "Цена": "28067грн",
        "Доставка": "7017"
    },
    {
        "Название": "рычаг левый acura rsx integra dc5 2001 2006",
        "Цена": "1812грн",
        "Доставка": "454"
    },
    {
        "Название": "обогреватель acura rsx хонда 2001 2007 европа",
        "Цена": "5746грн",
        "Доставка": "1437"
    },
    {
        "Название": "acura tl и 95-98 контроллер модуль 39880sl5a010m1",
        "Цена": "920грн",
        "Доставка": "230"
    },
    {
        "Название": "стекло кузовная, кузовной правая задней зад acura mdx ii 07-",
        "Цена": "3572грн",
        "Доставка": "893"
    },
    {
        "Название": "блок розжига ксенон, ксенону хонда acura tl tsx 33119-ta0-00",
        "Цена": "2254грн",
        "Доставка": "564"
    },
    {
        "Название": "acura tsx airbag подушка водитель, водителем ремни",
        "Цена": "7061грн",
        "Доставка": "1766"
    },
    {
        "Название": "acura tsx airbag подушка водитель, водителем ремни",
        "Цена": "7061грн",
        "Доставка": "1766"
    },
    {
        "Название": "acura tlx 2015 2016 2017 бампер перед usa",
        "Цена": "15667грн",
        "Доставка": "3917"
    },
    {
        "Название": "трос тормоза ручного левая, левой acura mdx ii 3. 7 07-13",
        "Цена": "2245грн",
        "Доставка": "562"
    },
    {
        "Название": "acura tsx airbag подушка воздух водитель, водителем",
        "Цена": "4430грн",
        "Доставка": "1108"
    },
    {
        "Название": "acura tsx airbag подушка воздух водитель, водителем",
        "Цена": "4430грн",
        "Доставка": "1108"
    },
    {
        "Название": "хонда nsx acura крышка залива топлива",
        "Цена": "3580грн",
        "Доставка": "896"
    },
    {
        "Название": "хонда acura tsx руль воздуха 19025-rl2-g00",
        "Цена": "1370грн",
        "Доставка": "343"
    },
    {
        "Название": "хонда nsx acura часы дисплей",
        "Цена": "3315грн",
        "Доставка": "829"
    },
    {
        "Название": "acura nsx компьютер 39900-sl0-013 поврежденный, поврежден",
        "Цена": "1370грн",
        "Доставка": "343"
    },
    {
        "Название": "хонда acura nsx air сумка шторка безопасности шторка безопасности левая, левой правая",
        "Цена": "21804грн",
        "Доставка": "5451"
    },
    {
        "Название": "хонда acura nsx стойки перед зад 2018 комплект.",
        "Цена": "134359грн",
        "Доставка": "33590"
    },
    {
        "Название": "хонда acura nsx 2018 дверь левый правое",
        "Цена": "126403грн",
        "Доставка": "31601"
    },
    {
        "Название": "стекло сторона правый зад хонда acura tsx 73441-tl0",
        "Цена": "1812грн",
        "Доставка": "454"
    },
    {
        "Название": "хонда acura nsx крышка задней комплект. с стекло",
        "Цена": "211636грн",
        "Доставка": "52909"
    },
    {
        "Название": "хонда acura nsx 2018 крыло правый перед",
        "Цена": "68544грн",
        "Доставка": "17136"
    },
    {
        "Название": "хонда acura nsx 2018 бампер зад комплект.",
        "Цена": "151597грн",
        "Доставка": "37900"
    },
    {
        "Название": "хонда acura nsx подкрылок перед зад левый правое",
        "Цена": "13569грн",
        "Доставка": "3393"
    },
    {
        "Название": "хонда acura nsx комплект. фар, отражателей зад лед 2018",
        "Цена": "43345грн",
        "Доставка": "10837"
    },
    {
        "Название": "хонда acura nsx 2018 крыло левый правый зад",
        "Цена": "212508грн",
        "Доставка": "53127"
    },
    {
        "Название": "хонда acura nsx 2018 стоп света стопу, сплаву зад",
        "Цена": "34735грн",
        "Доставка": "8684"
    },
    {
        "Название": "хонда acura nsx 2018 накладки листви порог",
        "Цена": "39404грн",
        "Доставка": "9852"
    },
    {
        "Название": "хонда acura nsx патрон капота 2018",
        "Цена": "14353грн",
        "Доставка": "3589"
    },
    {
        "Название": "хонда acura nsx 2018 монтаж багажника зад",
        "Цена": "77341грн",
        "Доставка": "19336"
    },
    {
        "Название": "хонда acura nsx 2018 защиты элементы багажника зад",
        "Цена": "21847грн",
        "Доставка": "5462"
    },
    {
        "Название": "хонда acura nsx 2018 жабо",
        "Цена": "21847грн",
        "Доставка": "5462"
    },
    {
        "Название": "хонда acura nsx 2017- балка бампера задний зад",
        "Цена": "43688грн",
        "Доставка": "10923"
    },
    {
        "Название": "хонда acura nsx 2018 зеркало левый правое зеркала",
        "Цена": "60001грн",
        "Доставка": "15001"
    },
    {
        "Название": "хонда nsx acura дверь правое 91-05",
        "Цена": "23065грн",
        "Доставка": "5767"
    },
    {
        "Название": "хонда nsx acura крышка зад задней",
        "Цена": "7939грн",
        "Доставка": "1985"
    },
    {
        "Название": "насос abs хонда acura 2. 5",
        "Цена": "1260грн",
        "Доставка": "315"
    },
    {
        "Название": "листва вертикальный дверь левый левая, левой зад acura mdx ii 09",
        "Цена": "1538грн",
        "Доставка": "385"
    },
    {
        "Название": "листва скребок правая правый зад acura mdx ii 08",
        "Цена": "1812грн",
        "Доставка": "454"
    },
    {
        "Название": "acura mdx рестайлинг 2017-2020 капот перед крышка крышка",
        "Цена": "19584грн",
        "Доставка": "4896"
    },
    {
        "Название": "acura tl 2009- капот перед крышка крышка",
        "Цена": "17835грн",
        "Доставка": "4459"
    },
    {
        "Название": "пружина амортизатор перед правый acura mdx 3. 5 03-",
        "Цена": "2873грн",
        "Доставка": "719"
    },
    {
        "Название": "модуль контроллер среднего замка acura mdx ii 07-",
        "Цена": "2245грн",
        "Доставка": "562"
    },
    {
        "Название": "acura rdx 2019 2020- капот перед крышка крышка",
        "Цена": "23936грн",
        "Доставка": "5984"
    },
    {
        "Название": "компресор кондиционера acura tl 2007r 3. 2",
        "Цена": "5746грн",
        "Доставка": "1437"
    },
    {
        "Название": "acura lt балка бампера перед",
        "Цена": "5746грн",
        "Доставка": "1437"
    },
    {
        "Название": "acura mdx 2007-2009 натяжитель",
        "Цена": "1547грн",
        "Доставка": "387"
    },
    {
        "Название": "листва скребок правая правый перед acura mdx ii",
        "Цена": "1812грн",
        "Доставка": "454"
    },
    {
        "Название": "ручка дверь правый зад правая задней acura mdx ii 09",
        "Цена": "1812грн",
        "Доставка": "454"
    },
    {
        "Название": "сиденья диван хонда legend iv 06-12 acura rl",
        "Цена": "11089грн",
        "Доставка": "2773"
    },
    {
        "Название": "acura rdx 2019- балка бампера перед усиление",
        "Цена": "13535грн",
        "Доставка": "3384"
    },
    {
        "Название": "acura rdx 2019 2020- бампер перед передний",
        "Цена": "16964грн",
        "Доставка": "4242"
    },
    {
        "Название": "бачок бак компенсаторный acura mdx ii 07-",
        "Цена": "2068грн",
        "Доставка": "518"
    },
    {
        "Название": "стекло сторона правая зад задней acura mdx 1 и 03r",
        "Цена": "1260грн",
        "Доставка": "315"
    },
    {
        "Название": "acura ilx 2013- фара фара правая перед usa",
        "Цена": "13535грн",
        "Доставка": "3384"
    },
    {
        "Название": "полуось шрус acura alfa romeo aston martin audi",
        "Цена": "1812грн",
        "Доставка": "454"
    },
    {
        "Название": "ремень панель  bezpieczenstwa левый центральный acura mdx ii 07-",
        "Цена": "1326грн",
        "Доставка": "332"
    },
    {
        "Название": "крыло левый зад четверть acura mdx 2007-2013",
        "Цена": "38728грн",
        "Доставка": "9682"
    },
    {
        "Название": "подушка водитель, водителем acura legend iv рестайлинг kb2 kb1",
        "Цена": "5123грн",
        "Доставка": "1281"
    },
    {
        "Название": "фара передней перед acura tl 2007r оригинал левая, левой",
        "Цена": "6184грн",
        "Доставка": "1547"
    },
    {
        "Название": "крышка залива топлива acura rsx integra type r dc5",
        "Цена": "1892грн",
        "Доставка": "473"
    },
    {
        "Название": "зеркало левый acura tl 2007r оригинал 9 pin",
        "Цена": "4022грн",
        "Доставка": "1006"
    },
    {
        "Название": "acura zdx крыло левый перед передний",
        "Цена": "22239грн",
        "Доставка": "5560"
    },
    {
        "Название": "защита стойки передний acura rsx integra dc5",
        "Цена": "1724грн",
        "Доставка": "431"
    },
    {
        "Название": "насос abs контроллер acura mdx и 03-06r хонда пульт, пульта",
        "Цена": "2696грн",
        "Доставка": "675"
    },
    {
        "Название": "защита противосолнечный acura tl iv 2009-2013 левая, левой",
        "Цена": "3138грн",
        "Доставка": "785"
    },
    {
        "Название": "полуось приводная левая, левой acura tsx 2. 4 2004-2008",
        "Цена": "4243грн",
        "Доставка": "1061"
    },
    {
        "Название": "хонда accord acura tsx порог левый листва порога",
        "Цена": "2828грн",
        "Доставка": "708"
    },
    {
        "Название": "хонда accord acura tsx порог правый листва порога",
        "Цена": "2828грн",
        "Доставка": "708"
    },
    {
        "Название": "хонда accord acura tsx порог левый листва порога",
        "Цена": "2828грн",
        "Доставка": "708"
    },
    {
        "Название": "хонда accord acura tsx порог правый листва порога",
        "Цена": "2828грн",
        "Доставка": "708"
    },
    {
        "Название": "acura tlx 2015 2016 2017 бампер перед решетка, решетки usa",
        "Цена": "19584грн",
        "Доставка": "4896"
    },
    {
        "Название": "сиденье сиденья 3 ряд, серии acura mdx 1 и 03r",
        "Цена": "2688грн",
        "Доставка": "672"
    },
    {
        "Название": "acura tl крепление бампера",
        "Цена": "1282грн",
        "Доставка": "321"
    },
    {
        "Название": "acura tl листва порога 2004",
        "Цена": "862грн",
        "Доставка": "216"
    },
    {
        "Название": "двигатель хонда 3. 2 v6 j32a accord acura tl v-tec",
        "Цена": "22239грн",
        "Доставка": "5560"
    },
    {
        "Название": "acura tl хонда листва тнвд форсунка",
        "Цена": "1282грн",
        "Доставка": "321"
    },
    {
        "Название": "acura tl хонда 3. 2 основа, основой фильтра масла, маслом",
        "Цена": "1282грн",
        "Доставка": "321"
    },
    {
        "Название": "acura tl 2004-2008 пружина",
        "Цена": "928грн",
        "Доставка": "233"
    },
    {
        "Название": "acura tl 2004-2008 защита противосолнечный",
        "Цена": "928грн",
        "Доставка": "233"
    },
    {
        "Название": "acura tl 2004-2008 держатель держатель",
        "Цена": "1060грн",
        "Доставка": "266"
    },
    {
        "Название": "acura tl 2004-2008 крышка защита",
        "Цена": "1060грн",
        "Доставка": "266"
    },
    {
        "Название": "acura tl 04-08 колесо, круг маховика",
        "Цена": "1282грн",
        "Доставка": "321"
    },
    {
        "Название": "acura tl 04-08 суппорт тормозной перед левый",
        "Цена": "1370грн",
        "Доставка": "343"
    },
    {
        "Название": "acura tl 04-08 стабилизатор",
        "Цена": "1282грн",
        "Доставка": "321"
    },
    {
        "Название": "acura tl 04-08 корпус термостату шланг линия",
        "Цена": "1370грн",
        "Доставка": "343"
    },
    {
        "Название": "acura tl 2004-2008 панель переключатель стекол",
        "Цена": "928грн",
        "Доставка": "233"
    },
    {
        "Название": "acura tl 2004-2008 ручка левая, левой",
        "Цена": "1060грн",
        "Доставка": "266"
    },
    {
        "Название": "acura tl 2004-2008 держатель держатель открытия капота",
        "Цена": "1060грн",
        "Доставка": "266"
    },
    {
        "Название": "acura tl 2004-2008 обшивка багажника",
        "Цена": "1016грн",
        "Доставка": "255"
    },
    {
        "Название": "acura tl 2004-2008 обшивка крышки",
        "Цена": "1060грн",
        "Доставка": "266"
    },
    {
        "Название": "acura tl 2004-2008 задней полка",
        "Цена": "1193грн",
        "Доставка": "299"
    },
    {
        "Название": "acura tl 2004-2008 защита",
        "Цена": "1193грн",
        "Доставка": "299"
    },
    {
        "Название": "acura tl обшивка дверь",
        "Цена": "928грн",
        "Доставка": "233"
    },
    {
        "Название": "хонда acura tl бампер зад задний b68p 97r.",
        "Цена": "3712грн",
        "Доставка": "929"
    },
    {
        "Название": "acura tl зеркало правое електрический, #ref!, эстетический. b68p 97r европа",
        "Цена": "1370грн",
        "Доставка": "343"
    },
    {
        "Название": "acura tl фара правый зад правая задней 97r. eu",
        "Цена": "1127грн",
        "Доставка": "282"
    },
    {
        "Название": "acura tl 04-08 педаль тормоза",
        "Цена": "1060грн",
        "Доставка": "266"
    },
    {
        "Название": "acura tl 2007 2008 зеркало наружное правое usa",
        "Цена": "4022грн",
        "Доставка": "1006"
    },
    {
        "Название": "решетка, решетки охладитель решетка acura tl 2009-2011",
        "Цена": "3572грн",
        "Доставка": "893"
    },
    {
        "Название": "стартер хонда accord acura tl 3. 2 31200-p5g-003",
        "Цена": "2475грн",
        "Доставка": "619"
    },
    {
        "Название": "дисплей обдува и радио acura tl 04-06",
        "Цена": "1193грн",
        "Доставка": "299"
    },
    {
        "Название": "фара задней зад acura tl 2007r оригинал",
        "Цена": "2696грн",
        "Доставка": "675"
    },
    {
        "Название": "радио панель кондиционера acura tl 2007r оригинал",
        "Цена": "4430грн",
        "Доставка": "1108"
    },
    {
        "Название": "зеркало правое левый acura tl 2007r оригинал",
        "Цена": "4022грн",
        "Доставка": "1006"
    },
    {
        "Название": "подушка двигателя acura tl 3. 2",
        "Цена": "3138грн",
        "Доставка": "785"
    },
    {
        "Название": "генератор acura tl 2007r 3. 2",
        "Цена": "3580грн",
        "Доставка": "896"
    },
    {
        "Название": "стартер acura tl 2007r 3. 2",
        "Цена": "3050грн",
        "Доставка": "763"
    },
    {
        "Название": "насос топлива acura tl 2007r 3. 2",
        "Цена": "3580грн",
        "Доставка": "896"
    },
    {
        "Название": "насос гидроусилителя acura tl 2007r 3. 2",
        "Цена": "4430грн",
        "Доставка": "1108"
    },
    {
        "Название": "коробка передач acura tl 3. 2 2007r",
        "Цена": "39028грн",
        "Доставка": "9757"
    },
    {
        "Название": "спидометр acura tl 2007r",
        "Цена": "4022грн",
        "Доставка": "Стоимость доставки не указана"
    },
    {
        "Название": "листва порога левая, левой acura rsx type s 2002 2006",
        "Цена": "2254грн",
        "Доставка": "564"
    },
    {
        "Название": "усиление балка перед dc5 acura rsx 2002 06",
        "Цена": "3748грн",
        "Доставка": "938"
    },
    {
        "Название": "вентилятор воды хонда acura rsx type s 2001 2007",
        "Цена": "1900грн",
        "Доставка": "476"
    },
    {
        "Название": "датчик детонации детонации acura mdx ii 3. 7 07-13",
        "Цена": "3138грн",
        "Доставка": "785"
    },
    {
        "Название": "датчик положения, выравнивания фар, отражателей ксенон, ксенону acura rsx dc5",
        "Цена": "3129грн",
        "Доставка": "783"
    },
    {
        "Название": "kamerka камера заднего вида, цифровой acura mdx ii 3. 7 2007-2009",
        "Цена": "2696грн",
        "Доставка": "675"
    },
    {
        "Название": "acura rlx 2014-2017 фара фара r full лед usa",
        "Цена": "26383грн",
        "Доставка": "6596"
    },
    {
        "Название": "acura rlx 2014-2017 фара фара левая, левой ксенон, ксенону лед",
        "Цена": "22239грн",
        "Доставка": "5560"
    },
    {
        "Название": "acura rlx 2014-2017 зеркало наружное левый usa",
        "Цена": "9183грн",
        "Доставка": "2296"
    },
    {
        "Название": "замок правый передний перед acura rl 06-12 keyless",
        "Цена": "1980грн",
        "Доставка": "496"
    },
    {
        "Название": "acura rl 2009- фара фара ксенон, ксенону правый usa",
        "Цена": "9174грн",
        "Доставка": "2294"
    },
    {
        "Название": "компьютер контроллер двигателя acura rl 06-09 хонда",
        "Цена": "4693грн",
        "Доставка": "1174"
    },
    {
        "Название": "компьютер контроллер двигателя acura rl 06-09 хонда",
        "Цена": "4693грн",
        "Доставка": "1174"
    },
    {
        "Название": "модуль bluetooth acura rl 06-2010 39770-sja-a012-m1",
        "Цена": "4013грн",
        "Доставка": "1004"
    },
    {
        "Название": "acura mdx 2014-2017 решетка решетка, решетки перед решетка, решетки",
        "Цена": "10924грн",
        "Доставка": "2731"
    },
    {
        "Название": "acura rdx компьютер 4992-102090 37820-rwc-a62",
        "Цена": "9096грн",
        "Доставка": "2274"
    },
    {
        "Название": "быстро стекло левая, левой треугольник acura rdx ii 2013-2018",
        "Цена": "1989грн",
        "Доставка": "498"
    },
    {
        "Название": "acura rdx рестайлинг 2016-2018 бампер перед передний",
        "Цена": "15232грн",
        "Доставка": "3808"
    },
    {
        "Название": "acura rdx 2006-2012 крышка зад задней багажника usa",
        "Цена": "16094грн",
        "Доставка": "4024"
    },
    {
        "Название": "acura rdx 2006- фара фара перед ксенон, ксенону l usa",
        "Цена": "13535грн",
        "Доставка": "3384"
    },
    {
        "Название": "acura rdx 2019 2020- зеркало наружное правое usa",
        "Цена": "13535грн",
        "Доставка": "3384"
    },
    {
        "Название": "зеркало левый acura rdx tl06nw21621 ix4 764379 13-",
        "Цена": "6623грн",
        "Доставка": "1656"
    },
    {
        "Название": "acura tl и 95-98 переключатель переключатель композитный",
        "Цена": "920грн",
        "Доставка": "230"
    },
    {
        "Название": "acura tl решетка, решетки решетка 75120-sw5-a01 75710-sw5-a01",
        "Цена": "1361грн",
        "Доставка": "341"
    },
    {
        "Название": "сигнал low acura mdx ii 3. 7 2007-2013",
        "Цена": "1184грн",
        "Доставка": "297"
    },
    {
        "Название": "защита нижняя защита днища acura mdx ii 3. 7 2007-2013",
        "Цена": "1361грн",
        "Доставка": "341"
    },
    {
        "Название": "трос газа acura mdx ii 3. 7 2007-2013",
        "Цена": "1812грн",
        "Доставка": "454"
    },
    {
        "Название": "трос переключения передач acura mdx ii 3. 7 2007-2013",
        "Цена": "2696грн",
        "Доставка": "675"
    },
    {
        "Название": "подлокотник дверь обшивка правый зад acura mdx ii",
        "Цена": "1096грн",
        "Доставка": "275"
    },
    {
        "Название": "подлокотник дверь обшивка правый перед acura mdx ii",
        "Цена": "1096грн",
        "Доставка": "275"
    },
    {
        "Название": "пластик защита ремня задний багажника acura mdx 08",
        "Цена": "2334грн",
        "Доставка": "584"
    },
    {
        "Название": "скоба суппорта зад задние, заднее  задней acura mdx ii 07-13",
        "Цена": "3218грн",
        "Доставка": "805"
    },
    {
        "Название": "суппорт левый зад задний задний acura mdx ii 2007-2013",
        "Цена": "3218грн",
        "Доставка": "805"
    },
    {
        "Название": "стекло дверь правый перед правая передней acura mdx",
        "Цена": "3572грн",
        "Доставка": "893"
    },
    {
        "Название": "стекло дверь правый зад правая передней acura mdx",
        "Цена": "3572грн",
        "Доставка": "893"
    },
    {
        "Название": "листва вертикальный дверь левый левая, левой зад acura mdx ii 09",
        "Цена": "1538грн",
        "Доставка": "385"
    },
    {
        "Название": "листва вертикальный дверь правый правая зад acura mdx ii",
        "Цена": "1538грн",
        "Доставка": "385"
    },
    {
        "Название": "листва вертикальный дверь правый правая зад acura mdx ii",
        "Цена": "1538грн",
        "Доставка": "385"
    },
    {
        "Название": "листва вертикальный дверь правый перед правая acura mdx",
        "Цена": "1538грн",
        "Доставка": "385"
    },
    {
        "Название": "листва вертикальный дверь левый перед левая, левой acura mdx ii",
        "Цена": "1538грн",
        "Доставка": "385"
    },
    {
        "Название": "защита крышка двигателя acura mdx пульт, пульта 3. 5 v6 03-",
        "Цена": "2121грн",
        "Доставка": "531"
    },
    {
        "Название": "торпедо подушка acura mdx 2007-2013",
        "Цена": "30399грн",
        "Доставка": "7600"
    },
    {
        "Название": "омыватель сопло крышки зад acura mdx 2007-2013",
        "Цена": "1361грн",
        "Доставка": "341"
    },
    {
        "Название": "мост зад задний дифференциал haldex acura mdx ii 2006-2013",
        "Цена": "8333грн",
        "Доставка": "2084"
    },
    {
        "Название": "полуось правая зад задней acura mdx ii 2006-2013",
        "Цена": "4430грн",
        "Доставка": "1108"
    },
    {
        "Название": "полуось левая, левой зад задней acura mdx ii 2006-2013",
        "Цена": "4430грн",
        "Доставка": "1108"
    },
    {
        "Название": "катализатор передний перед acura mdx 10-13 рестайлинг 3. 7",
        "Цена": "13535грн",
        "Доставка": "3384"
    },
    {
        "Название": "катализатор зад задний acura mdx ii 2007-2010 3. 7",
        "Цена": "13535грн",
        "Доставка": "3384"
    },
    {
        "Название": "хонда acura mdx фара левый правый 2004 2005-",
        "Цена": "6184грн",
        "Доставка": "1547"
    },
    {
        "Название": "acura tlx 2014- фара фара правая full лед usa",
        "Цена": "19619грн",
        "Доставка": "4905"
    },
    {
        "Название": "acura rdx 2019 2020- решетка решетка, решетки перед хром, хромом",
        "Цена": "9183грн",
        "Доставка": "2296"
    },
    {
        "Название": "левая, левой фара перед хонда legend купе 93r acura lege",
        "Цена": "1768грн",
        "Доставка": "442"
    },
    {
        "Название": "полуось передней левая, левой хонда legend iv kb1 kb-1 acura",
        "Цена": "4509грн",
        "Доставка": "1128"
    },
    {
        "Название": "фара usa ксенон, ксенону хонда acura legend 4 iv rl l",
        "Цена": "7061грн",
        "Доставка": "1766"
    },
    {
        "Название": "acura tl хонда legend 3. 2 v6 насос abs",
        "Цена": "1724грн",
        "Доставка": "431"
    },
    {
        "Название": "привод читатель dvd хонда legend iv acura rl kb-1",
        "Цена": "9174грн",
        "Доставка": "2294"
    },
    {
        "Название": "acura ilx 2013- фара фара ксенон, ксенону перед r usa",
        "Цена": "13535грн",
        "Доставка": "3384"
    },
    {
        "Название": "люк acura rsx integra dc5",
        "Цена": "3138грн",
        "Доставка": "785"
    },
    {
        "Название": "бак топлива насос acura rsx integra dc5",
        "Цена": "3757грн",
        "Доставка": "940"
    },
    {
        "Название": "подъемник стекла правый acura rsx integra dc5 eu",
        "Цена": "2334грн",
        "Доставка": "584"
    },
    {
        "Название": "подъемник стекла левый acura rsx integra dc5 lhd",
        "Цена": "3218грн",
        "Доставка": "805"
    },
    {
        "Название": "проводка дверь левый acura rsx integra dc5 eu",
        "Цена": "2696грн",
        "Доставка": "675"
    },
    {
        "Название": "вентилятор вентилятор воды acura rsx integra dc5",
        "Цена": "1361грн",
        "Доставка": "341"
    },
    {
        "Название": "вентилятор вентилятор климата acura rsx integra dc5",
        "Цена": "1361грн",
        "Доставка": "341"
    },
    {
        "Название": "балка бампера зад acura rl 71530-sja",
        "Цена": "6798грн",
        "Доставка": "1700"
    },
    {
        "Название": "фара левая, левой задней зад левый acura mdx ii 2010-2013",
        "Цена": "6535грн",
        "Доставка": "1634"
    },
    {
        "Название": "решетка, решетки решетка охладитель acura mdx ii рестайлинг 2010-2013",
        "Цена": "10924грн",
        "Доставка": "2731"
    },
    {
        "Название": "тормозные диски, диск перед 320mm acura хонда legend iv рестайлинг 3. 7",
        "Цена": "4430грн",
        "Доставка": "1108"
    },
    {
        "Название": "шторка безопасности airbag правая acura tl 2004-2008 curtain",
        "Цена": "2245грн",
        "Доставка": "562"
    },
    {
        "Название": "acura rdx 2013 в горе удлинение усиление перед",
        "Цена": "39028грн",
        "Доставка": "9757"
    },
    {
        "Название": "хонда integra acura rsx type r фара правая европа",
        "Цена": "9183грн",
        "Доставка": "2296"
    },
    {
        "Название": "плита защита под двигатель хонда acura mdx 14-19 usa",
        "Цена": "2254грн",
        "Доставка": "564"
    },
    {
        "Название": "коробка передач автомат acura cl [ya1] 3. v6 mcta",
        "Цена": "9661грн",
        "Доставка": "2416"
    },
    {
        "Название": "хонда acura 2001-2003 противотуманный передний правый",
        "Цена": "1361грн",
        "Доставка": "341"
    },
    {
        "Название": "крыло правый хонда acura 04-08",
        "Цена": "4199грн",
        "Доставка": "1050"
    },
    {
        "Название": "acura mdx 14-17 фара передней full лед левая, левой",
        "Цена": "26383грн",
        "Доставка": "6596"
    },
    {
        "Название": "колектор всасывающий дросель хонда acura mdx 3. 5 v6",
        "Цена": "4022грн",
        "Доставка": "1006"
    },
    {
        "Название": "acura tl зеркало левый електрический, #ref!, эстетический. b68p 97r европа",
        "Цена": "1370грн",
        "Доставка": "343"
    },
    {
        "Название": "защита крышка двигателя acura mdx ii 3. 7 2007-2009",
        "Цена": "3660грн",
        "Доставка": "915"
    },
    {
        "Название": "acura tl и механизм стекла електрические перед левый",
        "Цена": "1361грн",
        "Доставка": "341"
    },
    {
        "Название": "полуось левая, левой шрус зад acura mdx 1 и 3. 5 v6 03r",
        "Цена": "2688грн",
        "Доставка": "672"
    },
    {
        "Название": "спидометр спидометр acura mdx 1 и 3. 5 v6 03r",
        "Цена": "1804грн",
        "Доставка": "451"
    },
    {
        "Название": "acura tl генератор 2, 5 101211-9860 g25a4 cju86",
        "Цена": "2696грн",
        "Доставка": "675"
    },
    {
        "Название": "диски 5x114, 3 16 целые хонда accord acura tsr алюминиевые, алюминиевое",
        "Цена": "5614грн",
        "Доставка": "Стоимость доставки не указана"
    },
    {
        "Название": "фара крышки левая, левой задней зад acura mdx ii 2007-2009",
        "Цена": "4509грн",
        "Доставка": "1128"
    },
    {
        "Название": "acura mdx 2010-2013 решетка решетка, решетки перед",
        "Цена": "9183грн",
        "Доставка": "2296"
    },
    {
        "Название": "ручка левая, левой зад задней хонда acura tl 96r",
        "Цена": "920грн",
        "Доставка": "230"
    },
    {
        "Название": "acura tl и 95-98 ручка правая зад 72640-sw5-003z",
        "Цена": "920грн",
        "Доставка": "230"
    },
    {
        "Название": "acura tl стартер mitsuba sm-422 31200-p1r-a03",
        "Цена": "2254грн",
        "Доставка": "564"
    },
    {
        "Название": "стекло сторона левая, левой перед передней acura mdx 1 и 03r",
        "Цена": "1260грн",
        "Доставка": "315"
    },
    {
        "Название": "контроллер компьютер двигателя ecu acura mdx ii 3. 7 08",
        "Цена": "7061грн",
        "Доставка": "1766"
    },
    {
        "Название": "acura mdx 10-13 бампер зад",
        "Цена": "14318грн",
        "Доставка": "3580"
    },
    {
        "Название": "бачок гидроусилителя acura mdx ii 3. 7 2007-2013",
        "Цена": "1812грн",
        "Доставка": "454"
    },
    {
        "Название": "acura tl 2012 2013 2014 решетка решетка, решетки перед решетка, решетки",
        "Цена": "6623грн",
        "Доставка": "1656"
    },
    {
        "Название": "зеркало правое електрическое, электрическое  eu хонда acura 96r",
        "Цена": "1627грн",
        "Доставка": "407"
    },
    {
        "Название": "airbag подушка пасажира, пассажира acura mdx 1 и 03r",
        "Цена": "2245грн",
        "Доставка": "562"
    },
    {
        "Название": "зеркало внутренние средний внутренние acura mdx ii",
        "Цена": "2068грн",
        "Доставка": "518"
    },
    {
        "Название": "acura mdx 2014-2017 фара фара правая лед usa",
        "Цена": "22239грн",
        "Доставка": "5560"
    },
    {
        "Название": "acura mdx 2001-2006 бампер перед передний",
        "Цена": "6579грн",
        "Доставка": "1645"
    },
    {
        "Название": "acura mdx 2007- фара фара правая ксенон, ксенону usa",
        "Цена": "13535грн",
        "Доставка": "3384"
    },
    {
        "Название": "acura tl и реле mitsuba door lock rk-0278",
        "Цена": "1260грн",
        "Доставка": "315"
    },
    {
        "Название": "механизм моторчик стеклоочистителей acura mdx 1 и 03r",
        "Цена": "1184грн",
        "Доставка": "297"
    },
    {
        "Название": "динамики динамик боковой acura mdx ii 3. 7 07-13",
        "Цена": "1184грн",
        "Доставка": "297"
    },
    {
        "Название": "пенополистирол защита крыла утеплитель acura mdx ii",
        "Цена": "1184грн",
        "Доставка": "297"
    },
    {
        "Название": "моторчик очистителя зад acura mdx 1 и 03r",
        "Цена": "1361грн",
        "Доставка": "Стоимость доставки не указана"
    },
    {
        "Название": "рама стеклоочистителей acura mdx ii 3. 7 2007-2013",
        "Цена": "2696грн",
        "Доставка": "675"
    },
    {
        "Название": "сигнал high acura mdx ii 3. 7 2007-2013",
        "Цена": "1184грн",
        "Доставка": "297"
    },
    {
        "Название": "блок розжига ксенон, ксенону acura mdx ii 3. 7 2007-2009",
        "Цена": "2696грн",
        "Доставка": "675"
    },
    {
        "Название": "ручки крепления, направляющая радиаторов охладитель acura mdx ii",
        "Цена": "1538грн",
        "Доставка": "385"
    },
    {
        "Название": "панель кондиционера зад задний acura mdx ii 07-13",
        "Цена": "2245грн",
        "Доставка": "562"
    },
    {
        "Название": "усилитель аудио acura mdx ii 3. 7 2007-2009 2008",
        "Цена": "2696грн",
        "Доставка": "675"
    },
    {
        "Название": "потенциометр газа педаль acura mdx ii 3. 7 2007-2013",
        "Цена": "2245грн",
        "Доставка": "562"
    },
    {
        "Название": "подушка двигателя лапа, простынь acura mdx ii 3. 7 2007-2009",
        "Цена": "4013грн",
        "Доставка": "1004"
    },
    {
        "Название": "воспламенитель ксенон, ксенону acura mdx ii 3. 7 2007-2009",
        "Цена": "3218грн",
        "Доставка": "805"
    },
    {
        "Название": "контроллер приводов shawd acura mdx ii 3. 7 2007-09",
        "Цена": "4509грн",
        "Доставка": "1128"
    },
    {
        "Название": "шлейф дополнительная система удерживания руля acura mdx ii 3. 7 2007-2009",
        "Цена": "4860грн",
        "Доставка": "1215"
    },
    {
        "Название": "динамик центральный перед acura mdx ii 3. 7 07-13",
        "Цена": "1538грн",
        "Доставка": "385"
    },
    {
        "Название": "привод топливный шланг acura mdx ii 3. 7 2007-2013",
        "Цена": "1812грн",
        "Доставка": "454"
    },
    {
        "Название": "подъемник стекла левый передний перед acura mdx ii 09",
        "Цена": "4509грн",
        "Доставка": "1128"
    },
    {
        "Название": "acura tl 04-08 балка абсорбер бампера перед",
        "Цена": "2210грн",
        "Доставка": "553"
    },
    {
        "Название": "acura tl 2012 2013 2014 листва на решетка перед",
        "Цена": "3138грн",
        "Доставка": "785"
    },
    {
        "Название": "стекло дверь левый зад левая, левой задней acura mdx ii 07-13",
        "Цена": "3572грн",
        "Доставка": "893"
    },
    {
        "Название": "подъемник стекла левый перед передний acura mdx 1 и",
        "Цена": "1804грн",
        "Доставка": "451"
    },
    {
        "Название": "ручка дверь правый перед правая acura mdx ii 07-13",
        "Цена": "1812грн",
        "Доставка": "454"
    },
    {
        "Название": "пластик внутри защита acura mdx ii 2007-2013",
        "Цена": "1812грн",
        "Доставка": "454"
    },
    {
        "Название": "acura tl и 95-98 спидометр спидометр 157360-436103",
        "Цена": "1804грн",
        "Доставка": "451"
    },
    {
        "Название": "спидометр спидометр acura mdx ii km/h 3. 7 2008r",
        "Цена": "14405грн",
        "Доставка": "3602"
    },
    {
        "Название": "ремень панель  bezpieczenstwa центральный на крышу acura mdx ii",
        "Цена": "1326грн",
        "Доставка": "332"
    },
    {
        "Название": "стекло кузовная, кузовной правая зад acura mdx 1 и 03r",
        "Цена": "1184грн",
        "Доставка": "297"
    },
    {
        "Название": "стартер sm-422 хонда acura 2. 5 r5 96r",
        "Цена": "1804грн",
        "Доставка": "451"
    },
    {
        "Название": "галоген правый перед передний acura mdx 1 и 03r",
        "Цена": "1361грн",
        "Доставка": "341"
    },
    {
        "Название": "бампер acura mdx 71101-s3vx-zz00",
        "Цена": "16537грн",
        "Доставка": "4135"
    },
    {
        "Название": "acura tl и 95-98 контроллер модуль 28100-p1r-a05",
        "Цена": "2245грн",
        "Доставка": "562"
    },
    {
        "Название": "ручка внутренняя, внутри левая, левой зад задней acura mdx 1 и 03r",
        "Цена": "1114грн",
        "Доставка": "279"
    },
    {
        "Название": "acura tl панель управления печкой 79600-sw5-c41",
        "Цена": "1361грн",
        "Доставка": "341"
    },
    {
        "Название": "кнопка дверь стекла правый перед acura mdx ii 07-",
        "Цена": "1361грн",
        "Доставка": "341"
    },
    {
        "Название": "acura mdx 2017- full лед правый usa фара фара",
        "Цена": "30701грн",
        "Доставка": "7676"
    },
    {
        "Название": "листва скребок левая, левой левый перед acura mdx ii 08",
        "Цена": "1812грн",
        "Доставка": "454"
    },
    {
        "Название": "пластик внутри декор защита acura mdx ii 07-09",
        "Цена": "2696грн",
        "Доставка": "675"
    },
    {
        "Название": "контроллер 37820rdja560 acura mdx 1 и 3. 5 v6 03r",
        "Цена": "4860грн",
        "Доставка": "1215"
    },
    {
        "Название": "зеркало стекло вклад правое правый acura tl 09-14",
        "Цена": "1538грн",
        "Доставка": "385"
    },
    {
        "Название": "acura tl и 95-98 амортизатор перед p 51605-sw5-a02",
        "Цена": "1008грн",
        "Доставка": "252"
    },
    {
        "Название": "acura tl и 95-98 зеркало правое 76200-sw5-a22z",
        "Цена": "1361грн",
        "Доставка": "341"
    },
    {
        "Название": "acura tl и 95-98 пружина перед 2, 5 51401-sw5-j13",
        "Цена": "1184грн",
        "Доставка": "297"
    },
    {
        "Название": "панель регулировки, контроля  зеркала хонда acura 96r",
        "Цена": "1114грн",
        "Доставка": "279"
    },
    {
        "Название": "крепление бампера хонда acura 71509sea000",
        "Цена": "884грн",
        "Доставка": "221"
    },
    {
        "Название": "диск хонда acura mdx rlx 8, 5x20 et50 5x114 3",
        "Цена": "7492грн",
        "Доставка": "1873"
    },
    {
        "Название": "суппорт тормозной правый перед хонда acura tl 2. 5 r5",
        "Цена": "1361грн",
        "Доставка": "341"
    },
    {
        "Название": "пластик внутри декор защита acura mdx ii pt",
        "Цена": "1538грн",
        "Доставка": "385"
    },
    {
        "Название": "acura tl полуось левая, левой g25a4 44011-sw5-950",
        "Цена": "1812грн",
        "Доставка": "454"
    },
    {
        "Название": "acura tl и 95-98 реле denso 056700-9340",
        "Цена": "981грн",
        "Доставка": "246"
    },
    {
        "Название": "бардачок декор ролета acura mdx ii 2007-2013 3. 7",
        "Цена": "2696грн",
        "Доставка": "675"
    },
    {
        "Название": "пластик внутри декор защита acura mdx ii pp 08",
        "Цена": "1538грн",
        "Доставка": "385"
    },
    {
        "Название": "панель управления печкой климата хонда acura 96r",
        "Цена": "1273грн",
        "Доставка": "319"
    },
    {
        "Название": "acura tl и 95-98 блок abs mitsuba ab-04",
        "Цена": "1804грн",
        "Доставка": "451"
    },
    {
        "Название": "спидометр speedometer acura tl 3. 7 2012-2015 km/h",
        "Цена": "13535грн",
        "Доставка": "3384"
    },
    {
        "Название": "катушка зажигания хонда acura mdx 3. 5 v6 03-06r",
        "Цена": "928грн",
        "Доставка": "233"
    },
    {
        "Название": "насос гидроусилителя acura mdx ii 3. 7 2007-2013",
        "Цена": "7061грн",
        "Доставка": "1766"
    },
    {
        "Название": "acura tl и 95-98 контроллер модуль 39880sl5a010m1",
        "Цена": "920грн",
        "Доставка": "230"
    },
    {
        "Название": "зеркало правое 11 pin acura mdx ii nh737m 2007-13",
        "Цена": "7149грн",
        "Доставка": "1788"
    },
    {
        "Название": "панель управления печкой климата acura mdx 1 и 03r",
        "Цена": "1361грн",
        "Доставка": "341"
    },
    {
        "Название": "замок дверь левый задний зад acura mdx ii 3. 7 07-13",
        "Цена": "1812грн",
        "Доставка": "454"
    },
    {
        "Название": "насос гидроусилителя acura mdx 1 и 3. 5 v6 03r",
        "Цена": "6614грн",
        "Доставка": "1654"
    },
    {
        "Название": "стекло дверь левый перед левая, левой передней acura mdx ii",
        "Цена": "3572грн",
        "Доставка": "893"
    },
    {
        "Название": "acura tl и фара правый stanley, стэнли 033-6688r",
        "Цена": "1804грн",
        "Доставка": "451"
    },
    {
        "Название": "acura tl 2009-2014 капот перед крышка крышка usa",
        "Цена": "17835грн",
        "Доставка": "4459"
    },
    {
        "Название": "подъемник стекла левый зад задний acura mdx ii 07-13",
        "Цена": "3218грн",
        "Доставка": "805"
    },
    {
        "Название": "acura tl и 95-98 реле модуль 38600-sv7-a12",
        "Цена": "920грн",
        "Доставка": "230"
    },
    {
        "Название": "acura tl и 95-98 суппорт перед правый 45018-sw5-003",
        "Цена": "1804грн",
        "Доставка": "451"
    },
    {
        "Название": "модуль airbag acura mdx ii 77960-stx-a211-m1",
        "Цена": "6711грн",
        "Доставка": "1678"
    },
    {
        "Название": "acura tl 2004 трос залива топлива",
        "Цена": "1060грн",
        "Доставка": "266"
    },
    {
        "Название": "модуль компьютер дополнительная система удерживания контроллер acura mdx ii 2007-09",
        "Цена": "6535грн",
        "Доставка": "1634"
    },
    {
        "Название": "моторчик очистителя зад задний крышки acura mdx ii",
        "Цена": "5307грн",
        "Доставка": "1327"
    },
    {
        "Название": "замок привод крышки зад задний acura mdx ii 07-13",
        "Цена": "3218грн",
        "Доставка": "805"
    },
    {
        "Название": "спойлер дифузор бампера зад acura mdx 14-16 f. vat",
        "Цена": "1812грн",
        "Доставка": "454"
    },
    {
        "Название": "зеркало правое електрическое, электрическое  acura mdx 1 и 03r",
        "Цена": "1804грн",
        "Доставка": "451"
    },
    {
        "Название": "жабо пластик acura mdx ii 2007-2013 3. 7",
        "Цена": "4509грн",
        "Доставка": "1128"
    },
    {
        "Название": "листва скребок левая, левой левый зад acura mdx ii 07-",
        "Цена": "1812грн",
        "Доставка": "454"
    },
    {
        "Название": "acura ilx 2013- фара левый фара левая, левой перед",
        "Цена": "13535грн",
        "Доставка": "3384"
    },
    {
        "Название": "ремень панель  bezpieczenstwa правый зад задний acura mdx ii 09",
        "Цена": "1326грн",
        "Доставка": "332"
    },
    {
        "Название": "хонда acura mdx рестайлинг 04-06 бампер зад парктроники",
        "Цена": "7720грн",
        "Доставка": "1930"
    },
    {
        "Название": "acura mdx 2007- фара фара левая, левой ксенон, ксенону usa",
        "Цена": "13535грн",
        "Доставка": "3384"
    },
    {
        "Название": "замок дверь перед передний левый acura mdx 03-06r",
        "Цена": "2254грн",
        "Доставка": "564"
    },
    {
        "Название": "acura tl рестайлинг 04-06r - бампер перед передний",
        "Цена": "9574грн",
        "Доставка": "2394"
    },
    {
        "Название": "acura tl и 95-98 панель печкой 79600sw5a41 sw-a",
        "Цена": "1361грн",
        "Доставка": "341"
    },
    {
        "Название": "подъемник стекла правый перед передний acura mdx 1 и",
        "Цена": "1361грн",
        "Доставка": "341"
    },
    {
        "Название": "радиатор коробки передач acura mdx ii 3. 7 07-2013",
        "Цена": "6535грн",
        "Доставка": "1634"
    },
    {
        "Название": "радио кассеты, футляри кассета cd rds acura mdx 1 и 03r",
        "Цена": "4860грн",
        "Доставка": "1215"
    },
    {
        "Название": "acura ilx 2013- фара левый ксенон, ксенону фара перед",
        "Цена": "17887грн",
        "Доставка": "4472"
    },
    {
        "Название": "acura tl и 95-98 рычаг верхний, горы правый 51450-sl5-961",
        "Цена": "920грн",
        "Доставка": "230"
    },
    {
        "Название": "acura tl 95-98 стабилизатор стабилизатора 51300-sw5-a01",
        "Цена": "1804грн",
        "Доставка": "451"
    },
    {
        "Название": "стекло сторона левая, левой зад задней acura mdx 1 и 03r",
        "Цена": "1260грн",
        "Доставка": "315"
    },
    {
        "Название": "резонатор воздуха acura mdx ii 2007-2013 3. 7",
        "Цена": "4013грн",
        "Доставка": "1004"
    },
    {
        "Название": "acura tl полуось правая g25a4 44010-sw5-950",
        "Цена": "1812грн",
        "Доставка": "454"
    },
    {
        "Название": "генератор хонда ahga55 civic acura k20a k20a1",
        "Цена": "1812грн",
        "Доставка": "454"
    },
    {
        "Название": "замок крышки зад задней acura mdx 1 и 03r",
        "Цена": "1361грн",
        "Доставка": "341"
    },
    {
        "Название": "держатель рама стеклоочистителей acura mdx 1 и 03r",
        "Цена": "1114грн",
        "Доставка": "279"
    },
    {
        "Название": "пластик внутри декор защита acura mdx ii 07-09",
        "Цена": "2696грн",
        "Доставка": "675"
    },
    {
        "Название": "вентилятор хонда acura 2. 5 r5 96r",
        "Цена": "920грн",
        "Доставка": "230"
    },
    {
        "Название": "acura mdx рестайлинг 2017-2020 капот перед крышка крышка",
        "Цена": "23936грн",
        "Доставка": "5984"
    },
    {
        "Название": "диск алюминиевая acura nsx хонда 15x6, 5 et55",
        "Цена": "2077грн",
        "Доставка": "520"
    },
    {
        "Название": "acura tl и 95-98 модуль 36700-sw5-a01 rk-0417",
        "Цена": "1260грн",
        "Доставка": "315"
    },
    {
        "Название": "асферический зеркало acura tl ua8 2008-2014 2013 2012",
        "Цена": "1264грн",
        "Доставка": "Стоимость доставки не указана"
    },
    {
        "Название": "acura tl фара правый 33101-sw5-a01 033-6688r",
        "Цена": "1804грн",
        "Доставка": "451"
    },
    {
        "Название": "acura tl 95- двигатель крышки обогревателя 0637006720",
        "Цена": "1184грн",
        "Доставка": "297"
    },
    {
        "Название": "полуось левая, левой перед левый acura mdx ii 3. 7 2007-2009",
        "Цена": "9174грн",
        "Доставка": "2294"
    },
    {
        "Название": "acura tl и 95-98 реле модуль mitsuba rz-0117",
        "Цена": "1008грн",
        "Доставка": "252"
    },
    {
        "Название": "замок дверь правый передний перед acura mdx ii 07-13",
        "Цена": "1812грн",
        "Доставка": "454"
    },
    {
        "Название": "acura tl 95- цапфа левая, левой перед 51215-sw5-j60",
        "Цена": "1184грн",
        "Доставка": "297"
    },
    {
        "Название": "компресор кондиционера acura mdx ii 3. 7 2007-2013",
        "Цена": "10488грн",
        "Доставка": "2623"
    },
    {
        "Название": "пластик внутри декор защита acura mdx ii 07-09",
        "Цена": "2696грн",
        "Доставка": "675"
    },
    {
        "Название": "acura tl 95-98 указатель поворота, указательный столб правый 33801-sw5-a01",
        "Цена": "1008грн",
        "Доставка": "252"
    },
    {
        "Название": "брызговики хонда integra dc2 acura 94-01 перед зад",
        "Цена": "1804грн",
        "Доставка": "451"
    },
    {
        "Название": "листва порога правая acura tl iv 4 09-11 накладка",
        "Цена": "4022грн",
        "Доставка": "1006"
    },
    {
        "Название": "насос топлива поплавок acura mdx ii 3. 7 2007-2013",
        "Цена": "2696грн",
        "Доставка": "675"
    },
    {
        "Название": "бампер задний хонда acura 04-08 nr 9975",
        "Цена": "1944грн",
        "Доставка": "487"
    },
    {
        "Название": "хонда acura nsx 2018 система выпускной",
        "Цена": "160437грн",
        "Доставка": "40110"
    },
    {
        "Название": "защита стойки пластик правый acura mdx ii 07-13 3. 7",
        "Цена": "1812грн",
        "Доставка": "454"
    },
    {
        "Название": "замок дверь правый зад задний acura mdx 1 и 03r",
        "Цена": "920грн",
        "Доставка": "230"
    },
    {
        "Название": "acura tl компьютер 37820p1r a52 100797-7133 denso",
        "Цена": "1804грн",
        "Доставка": "451"
    },
    {
        "Название": "привод кондиционера acura mdx ii 3. 7 2007-2013",
        "Цена": "7061грн",
        "Доставка": "1766"
    },
    {
        "Название": "airbag подушка водитель, водителем хонда acura 96r",
        "Цена": "1114грн",
        "Доставка": "279"
    },
    {
        "Название": "acura tl бампер передний перед",
        "Цена": "6140грн",
        "Доставка": "1536"
    },
    {
        "Название": "пластик внутри декор листва acura mdx ii 07-09",
        "Цена": "1184грн",
        "Доставка": "297"
    },
    {
        "Название": "acura tl 2004 2005 2006 листва на решетка перед",
        "Цена": "2696грн",
        "Доставка": "675"
    },
    {
        "Название": "бачок моторчик омыватели acura mdx 1 и",
        "Цена": "1361грн",
        "Доставка": "341"
    },
    {
        "Название": "замок дверь левый зад задний acura mdx 1 и 03r",
        "Цена": "920грн",
        "Доставка": "230"
    },
    {
        "Название": "бачок омыватели acura mdx ii 3. 7 2007-13",
        "Цена": "1538грн",
        "Доставка": "385"
    },
    {
        "Название": "acura mdx 2007-2010 решетка решетка, решетки перед решетка, решетки",
        "Цена": "7061грн",
        "Доставка": "1766"
    },
    {
        "Название": "хонда acura nsx 2018 комплект колеса",
        "Цена": "169719грн",
        "Доставка": "42430"
    },
    {
        "Название": "катушка катушки зажигания acura mdx 07-13 3. 7",
        "Цена": "1804грн",
        "Доставка": "451"
    },
    {
        "Название": "вентилятор охладитель acura mdx ii 3. 7 2007-2013",
        "Цена": "6448грн",
        "Доставка": "1612"
    },
    {
        "Название": "переключатель спаренний паук, звёздочек  хонда acura 96r",
        "Цена": "920грн",
        "Доставка": "230"
    },
    {
        "Название": "acura tl и 95-98 реле denso 056800-1120",
        "Цена": "981грн",
        "Доставка": "246"
    },
    {
        "Название": "acura tl моторчик стеклоочистителей перед 76505-sv4-a01",
        "Цена": "1361грн",
        "Доставка": "341"
    },
    {
        "Название": "пластик накладка порога acura mdx ii левый зад 07-",
        "Цена": "1184грн",
        "Доставка": "297"
    },
    {
        "Название": "стекло кузовная, кузовной левая, левой зад acura mdx 1 и 03r",
        "Цена": "1184грн",
        "Доставка": "297"
    },
    {
        "Название": "ремень панель  bezpieczenstwa левый зад задний acura mdx ii 07-",
        "Цена": "1326грн",
        "Доставка": "332"
    },
    {
        "Название": "панель управления стекол водитель, водителем acura mdx 1 и 03r",
        "Цена": "1260грн",
        "Доставка": "315"
    },
    {
        "Название": "acura tl и 95-98 ручка правая зад 72620-sw5-003",
        "Цена": "1114грн",
        "Доставка": "279"
    },
    {
        "Название": "acura tl привод замка зад левый 72655-sw5-a01",
        "Цена": "1114грн",
        "Доставка": "279"
    },
    {
        "Название": "рычаг передний нижний правый acura mdx ii 2007-2013",
        "Цена": "8202грн",
        "Доставка": "2051"
    },
    {
        "Название": "моторчик стеклоочистителей перед acura mdx ii 3. 7 07-13",
        "Цена": "2245грн",
        "Доставка": "562"
    },
    {
        "Название": "acura tl 71501-tk4-a100 12-14r. бампер зад gda",
        "Цена": "8596грн",
        "Доставка": "2150"
    },
    {
        "Название": "acura tl 2004 модуль подвеска",
        "Цена": "1060грн",
        "Доставка": "266"
    },
    {
        "Название": "acura tl и 95-98 пружина перед 2, 5 51401-sw5-j13",
        "Цена": "1184грн",
        "Доставка": "297"
    },
    {
        "Название": "acura tl 95-98 крышка залива топлива 63910-sw5-000z",
        "Цена": "1114грн",
        "Доставка": "279"
    },
    {
        "Название": "acura tl imechanizm стекла зад левый 72751-sl9-003",
        "Цена": "1184грн",
        "Доставка": "297"
    },
    {
        "Название": "фара крышки правая задней зад acura mdx ii 2007-2009",
        "Цена": "4509грн",
        "Доставка": "1128"
    },
    {
        "Название": "радиатор радиатор гидроусилителя acura mdx 07-13",
        "Цена": "4509грн",
        "Доставка": "1128"
    },
    {
        "Название": "acura tl 2009-2014 крышка зад задней багажника",
        "Цена": "25842грн",
        "Доставка": "6461"
    },
    {
        "Название": "подушка амортизатора правая левая, левой acura mdx ii 07-",
        "Цена": "2696грн",
        "Доставка": "675"
    },
    {
        "Название": "галоген противотуманный оригинал. до хонда, acura ford",
        "Цена": "884грн",
        "Доставка": "221"
    },
    {
        "Название": "пластик накладка порога acura mdx ii правый зад 08",
        "Цена": "1184грн",
        "Доставка": "297"
    },
    {
        "Название": "колонка рулевая полный acura mdx ii 3. 7 07-",
        "Цена": "2245грн",
        "Доставка": "562"
    },
    {
        "Название": "хонда acura стекло лобовое 2008 >",
        "Цена": "15928грн",
        "Доставка": "3983"
    },
    {
        "Название": "acura tl и 95-98 ручка правая перед 72140-sw5-y01",
        "Цена": "1260грн",
        "Доставка": "315"
    },
    {
        "Название": "ручка крышки зад задней acura mdx ii 3. 7 2007-2013",
        "Цена": "2245грн",
        "Доставка": "562"
    },
    {
        "Название": "подъемник стекла правый перед eu хонда acura 96r",
        "Цена": "1096грн",
        "Доставка": "275"
    },
    {
        "Название": "acura tl и 95-98 ручка левая, левой зад 72660-sw5-003",
        "Цена": "1114грн",
        "Доставка": "279"
    },
    {
        "Название": "шланг залива топлива бака залив acura mdx ii 3. 7 07-13",
        "Цена": "4013грн",
        "Доставка": "1004"
    },
    {
        "Название": "acura tl и 95-98 механизм передач 2, 5b автомат",
        "Цена": "1361грн",
        "Доставка": "341"
    },
    {
        "Название": "подъемник стекла правый зад задний acura mdx ii 07-13",
        "Цена": "3218грн",
        "Доставка": "805"
    },
    {
        "Название": "acura tl 2004 крышка залива топлива",
        "Цена": "1060грн",
        "Доставка": "266"
    },
    {
        "Название": "acura tl катушка зажигания tc-17a 30510-pv1-a01",
        "Цена": "928грн",
        "Доставка": "233"
    },
    {
        "Название": "хонда acura 07-10 листва дверь перед правая!",
        "Цена": "1121грн",
        "Доставка": "Стоимость доставки не указана"
    },
    {
        "Название": "панель управления регулировкой, контроль зеркала хонда acura tl",
        "Цена": "1260грн",
        "Доставка": "315"
    },
    {
        "Название": "acura tl механизм стекла зад правый 72711-sl9-003",
        "Цена": "1184грн",
        "Доставка": "297"
    },
    {
        "Название": "acura tl и 95-98 указатель поворота, указательный столб левый 33351-sw5-a01",
        "Цена": "1184грн",
        "Доставка": "297"
    },
    {
        "Название": "вентилятор acura mdx 1 и 3. 5 v6 03r",
        "Цена": "920грн",
        "Доставка": "230"
    },
    {
        "Название": "acura tl коробка предохранители 38200-sw5-a82",
        "Цена": "920грн",
        "Доставка": "230"
    },
    {
        "Название": "acura tl 2009-2014 капот перед крышка крышка",
        "Цена": "19584грн",
        "Доставка": "4896"
    },
    {
        "Название": "хонда acura integra 1994- фара фара левая, левой eu",
        "Цена": "7500грн",
        "Доставка": "1876"
    },
    {
        "Название": "acura tl и 95-98 ручка левая, левой зад 72680-sw5-003z",
        "Цена": "920грн",
        "Доставка": "230"
    },
    {
        "Название": "пластик защита внутри acura mdx ii 2007-2013",
        "Цена": "1184грн",
        "Доставка": "297"
    },
    {
        "Название": "acura tl и механизм стекла електрические зад правый",
        "Цена": "1184грн",
        "Доставка": "297"
    },
    {
        "Название": "acura tl и 95-98 панель переключатель стекол перед левый",
        "Цена": "1361грн",
        "Доставка": "341"
    },
    {
        "Название": "acura tl и 95-98 ручка наружной правая перед",
        "Цена": "1260грн",
        "Доставка": "315"
    },
    {
        "Название": "суппорт тормозной левый перед хонда acura tl 2. 5 r5",
        "Цена": "1361грн",
        "Доставка": "341"
    },
    {
        "Название": "acura tl и 95-98 ручка наружной левая, левой перед",
        "Цена": "920грн",
        "Доставка": "230"
    },
    {
        "Название": "acura tl и 95-98 амортизатор перед 51602-sw5-a03",
        "Цена": "1008грн",
        "Доставка": "252"
    },
    {
        "Название": "вакуум тормозов acura mdx 1 и 3. 5 v6 03r",
        "Цена": "1361грн",
        "Доставка": "341"
    },
    {
        "Название": "ремень панель  bezpieczenstwa правый центральный acura mdx ii 09",
        "Цена": "1326грн",
        "Доставка": "332"
    },
    {
        "Название": "хонда acura 04-08 крыло левый wysylka24h",
        "Цена": "10436грн",
        "Доставка": "2610"
    },
    {
        "Название": "acura airbag подушки фишка, штекер, штекером kabael",
        "Цена": "994грн",
        "Доставка": "249"
    },
    {
        "Название": "подушка воздух airbag хонда acura 1995",
        "Цена": "1260грн",
        "Доставка": "315"
    },
    {
        "Название": "хонда acura решетка, решетки решетка гриль",
        "Цена": "1184грн",
        "Доставка": "297"
    },
    {
        "Название": "переключатель cruise control хонда acura",
        "Цена": "1260грн",
        "Доставка": "315"
    },
    {
        "Название": "acura tl решетка, решетки бампера левая, левой",
        "Цена": "1804грн",
        "Доставка": "451"
    },
    {
        "Название": "замок дверь левый перед передний acura mdx 1 и 03r",
        "Цена": "1184грн",
        "Доставка": "297"
    },
    {
        "Название": "acura tl и 95-98 переключатель стекол зад левый",
        "Цена": "920грн",
        "Доставка": "230"
    },
    {
        "Название": "acura tl и 95-98 переключатель 35255-sw5-a31",
        "Цена": "1114грн",
        "Доставка": "279"
    },
    {
        "Название": "acura tl механизм стекла перед правый 72210-sw5-a02",
        "Цена": "1361грн",
        "Доставка": "341"
    },
    {
        "Название": "37950-p5a-a02 модуль зажигание хонда acura",
        "Цена": "1016грн",
        "Доставка": "255"
    },
    {
        "Название": "кнопка аварийных подушки acura mdx ii 07-13",
        "Цена": "1361грн",
        "Доставка": "341"
    },
    {
        "Название": "стекло кузовная, кузовной левая, левой задней левый зад acura mdx ii",
        "Цена": "3572грн",
        "Доставка": "893"
    },
    {
        "Название": "подъемник стекла правый передний перед acura mdx ii",
        "Цена": "3218грн",
        "Доставка": "805"
    },
    {
        "Название": "acura tl и 95-98 часы 39700-sw5-a0 sw5-aoyr164l",
        "Цена": "920грн",
        "Доставка": "230"
    },
    {
        "Название": "acura tl и переключатель туманная, противотуманных cruise",
        "Цена": "920грн",
        "Доставка": "230"
    },
    {
        "Название": "галоген хонда acura",
        "Цена": "1370грн",
        "Доставка": "343"
    },
    {
        "Название": "acura tl и 95-98 ручка левая, левой перед 72183-sw3-013z",
        "Цена": "1184грн",
        "Доставка": "297"
    },
    {
        "Название": "пластик внутри декор листва acura mdx ii 07-09",
        "Цена": "1184грн",
        "Доставка": "297"
    },
    {
        "Название": "acura tl механизм стекла перед левый 72250-sw5-a02",
        "Цена": "1361грн",
        "Доставка": "341"
    },
    {
        "Название": "антенна acura mdx ii 3. 7 2007-2013",
        "Цена": "1812грн",
        "Доставка": "454"
    },
    {
        "Название": "acura tl и 95-98 замок перед передний левый",
        "Цена": "920грн",
        "Доставка": "230"
    },
    {
        "Название": "пластик накладка порога acura mdx ii правая перед",
        "Цена": "1184грн",
        "Доставка": "297"
    },
    {
        "Название": "acura tl и 95-98 фара зад правая 33501-sw5-a01",
        "Цена": "920грн",
        "Доставка": "230"
    },
    {
        "Название": "пластик накладка порога acura mdx ii левый перед",
        "Цена": "1184грн",
        "Доставка": "297"
    },
    {
        "Название": "привод кондиционера acura mdx ii 3. 7 2007-2013",
        "Цена": "3572грн",
        "Доставка": "893"
    },
    {
        "Название": "защита стойки пластик левый левая, левой acura mdx ii 07-13",
        "Цена": "1812грн",
        "Доставка": "454"
    },
    {
        "Название": "acura tl и 95-98 замок зад задний левый",
        "Цена": "1114грн",
        "Доставка": "279"
    },
    {
        "Название": "acura tl и механизм стекла електрические зад левый 4d",
        "Цена": "1184грн",
        "Доставка": "297"
    },
    {
        "Название": "брызговик левый передний acura mdx ii 3. 7 2010-2013",
        "Цена": "1812грн",
        "Доставка": "454"
    },
    {
        "Название": "насос abs 006v95148c acura mdx 1 и 3. 5 v6 03r",
        "Цена": "3129грн",
        "Доставка": "783"
    },
    {
        "Название": "acura tl и 95-98 переключатель света, свет, светофоров аварийных",
        "Цена": "920грн",
        "Доставка": "230"
    },
    {
        "Название": "рейка рейка рулевая, рейка eu хонда acura 2. 5 r5 96r",
        "Цена": "2952грн",
        "Доставка": "739"
    },
    {
        "Название": "замок дверь правый перед передний хонда acura tl 96r",
        "Цена": "1114грн",
        "Доставка": "279"
    },
    {
        "Название": "acura tl и 95-98 реле модуль 37740-p1r-a01",
        "Цена": "1184грн",
        "Доставка": "297"
    },
    {
        "Название": "acura tl 95-98 указатель поворота, указательный столб левый 33851-sw5-a01",
        "Цена": "1008грн",
        "Доставка": "252"
    },
    {
        "Название": "пластик внутри декор защита acura mdx ii 07-09",
        "Цена": "1361грн",
        "Доставка": "341"
    },
    {
        "Название": "acura tl door lock 72126-st7-a01z 35380-sz3-a01",
        "Цена": "1114грн",
        "Доставка": "279"
    },
    {
        "Название": "подъемник стекла левый перед eu хонда acura 1 и tl",
        "Цена": "1273грн",
        "Доставка": "319"
    },
    {
        "Название": "acura tl и 95-98 ручка наружной правая зад",
        "Цена": "920грн",
        "Доставка": "230"
    },
    {
        "Название": "acura tl и 95-98 замок перед передний правый",
        "Цена": "1008грн",
        "Доставка": "252"
    },
    {
        "Название": "acura tl и 95-98 реле модуль 39790-sw5-a02",
        "Цена": "1184грн",
        "Доставка": "297"
    },
    {
        "Название": "g-sensor сенсор датчик оборота acura mdx ii 07-13",
        "Цена": "2696грн",
        "Доставка": "675"
    },
    {
        "Название": "стекло сторона правая перед передней acura mdx 1 и",
        "Цена": "1260грн",
        "Доставка": "315"
    },
    {
        "Название": "расходомер 197400-0060 хонда acura 2. 5 r5 96r",
        "Цена": "1804грн",
        "Доставка": "451"
    },
    {
        "Название": "acura tl бак гидроусилителя 53701-sw3-003",
        "Цена": "928грн",
        "Доставка": "233"
    },
    {
        "Название": "acura tl компресор denso 447200-490 38810-p1e-003",
        "Цена": "4022грн",
        "Доставка": "1006"
    },
    {
        "Название": "пластик внутри защита acura mdx ii 2007-2013",
        "Цена": "1812грн",
        "Доставка": "454"
    },
    {
        "Название": "acura tl и 95-98 модуль 28100-p1r-a02 control unit",
        "Цена": "1008грн",
        "Доставка": "252"
    },
    {
        "Название": "панель управления стекол водитель, водителем хонда acura 96r",
        "Цена": "1008грн",
        "Доставка": "252"
    },
    {
        "Название": "acura tl и сенсор 77960sw5a820m1 152300-1172",
        "Цена": "920грн",
        "Доставка": "230"
    },
    {
        "Название": "механизм моторчик стеклоочистителей eu хонда acura 96r",
        "Цена": "920грн",
        "Доставка": "230"
    },
    {
        "Название": "acura tl door lock 72166-st7-a01z 35380-sz3-a01",
        "Цена": "1114грн",
        "Доставка": "279"
    },
    {
        "Название": "acura tl и 95-98 ручка правая перед 72120-sw5-003",
        "Цена": "1114грн",
        "Доставка": "279"
    },
    {
        "Название": "acura tl 95-98 замок зад правый 72615-sw5-a01",
        "Цена": "1114грн",
        "Доставка": "279"
    },
    {
        "Название": "acura tl 95-98 замок перед левый 72150-sw5-a01",
        "Цена": "1008грн",
        "Доставка": "252"
    },
    {
        "Название": "acura tl переключатель стекла правый перед 35760-sw5-003",
        "Цена": "920грн",
        "Доставка": "230"
    },
    {
        "Название": "acura tl 95-98 замок перед правый 72110-sw5-a01",
        "Цена": "1008грн",
        "Доставка": "252"
    },
    {
        "Название": "acura tl и 95-98 суппорт перед левый 45019-sw5-003",
        "Цена": "1804грн",
        "Доставка": "451"
    },
    {
        "Название": "acura tl и 95-98 переключатель переключатель стеклоочистителей",
        "Цена": "1260грн",
        "Доставка": "315"
    },
    {
        "Название": "свеча, светят зажигания acura chevrolet  daewoo daihatsu",
        "Цена": "838грн",
        "Доставка": "Стоимость доставки не указана"
    },
    {
        "Название": "acura tl и 95-98 ручка левая, левой перед 72160-sw5-003",
        "Цена": "1114грн",
        "Доставка": "279"
    },
    {
        "Название": "асферический acura ilx 2012-2019 2018 2017 2016 2015",
        "Цена": "3811грн",
        "Доставка": "Стоимость доставки не указана"
    },
    {
        "Название": "acura tl и 95-98 переключатель стекол 83771-sw5-j50zc",
        "Цена": "920грн",
        "Доставка": "230"
    },
    {
        "Название": "acura tl привод замка зад правый 72615-sw5-a01",
        "Цена": "1114грн",
        "Доставка": "279"
    },
    {
        "Название": "acura tl контроль, контрасту зеркала панель 35190-sw5-a11",
        "Цена": "920грн",
        "Доставка": "230"
    },
    {
        "Название": "acura tl 95-98 переключатель стекол правый зад",
        "Цена": "920грн",
        "Доставка": "230"
    },
    {
        "Название": "acura tl 2004-2008 модуль bluetooth",
        "Цена": "1193грн",
        "Доставка": "299"
    },
    {
        "Название": "acura tl 2004-2008 проводка проводка",
        "Цена": "928грн",
        "Доставка": "233"
    },
    {
        "Название": "зеркало левый електрическое, электрическое  eu хонда acura 96r",
        "Цена": "1361грн",
        "Доставка": "341"
    },
    {
        "Название": "диск 19 хонда acura 8x19 et55 5x120 tk5980a",
        "Цена": "5737грн",
        "Доставка": "1435"
    },
    {
        "Название": "вентилятор хонда acura 2. 5 r5 96r",
        "Цена": "920грн",
        "Доставка": "230"
    },
    {
        "Название": "programator ключи хонда acura",
        "Цена": "102146грн",
        "Доставка": "Стоимость доставки не указана"
    },
    {
        "Название": "контроллер 37820p1r a54 хонда acura 2. 5 r5 96r",
        "Цена": "1361грн",
        "Доставка": "341"
    },
    {
        "Название": "переключатель хонда crv, acura оригинала 36511-ppa-a01 denso",
        "Цена": "4022грн",
        "Доставка": "1006"
    },
    {
        "Название": "ручка левая, левой перед передней хонда acura 96r",
        "Цена": "920грн",
        "Доставка": "230"
    },
    {
        "Название": "sferyczny acura el 1997-2000 1998 1999 thomasss",
        "Цена": "1458грн",
        "Доставка": "Стоимость доставки не указана"
    }
]